{
  "description": "\n Small helper class to provide a small slice of a stream.", 
  "examples": [], 
  "id": "gcloud.streaming.stream_slice.streamslice", 
  "methods": [
    {
      "examples": [], 
      "exceptions": [], 
      "id": "gcloud.streaming.stream_slice.StreamSlice.__init__", 
      "name": "__init__", 
      "params": [], 
      "returns": [], 
      "source": "/home/travis/build/GoogleCloudPlatform/gcloud-python/.tox/json-docs/lib/python2.7/site-packages/gcloud/streaming/stream_slice.py/gcloud/streaming/stream_slice.py#L29", 
      "type": "instance"
    }, 
    {
      "examples": [], 
      "exceptions": [], 
      "id": "gcloud.streaming.stream_slice.StreamSlice.read", 
      "name": "read", 
      "params": [
        {
          "description": " If provided, read no more than size bytes from the stream.", 
          "name": "size", 
          "nullable": null, 
          "optional": null, 
          "types": [
            "integer or None"
          ]
        }
      ], 
      "returns": [
        {
          "types": [
            "bytes"
          ]
        }
      ], 
      "source": "/home/travis/build/GoogleCloudPlatform/gcloud-python/.tox/json-docs/lib/python2.7/site-packages/gcloud/streaming/stream_slice.py/gcloud/streaming/stream_slice.py#L59", 
      "type": "instance"
    }
  ], 
  "name": "Streamslice", 
  "source": "/home/travis/build/GoogleCloudPlatform/gcloud-python/.tox/json-docs/lib/python2.7/site-packages/gcloud/__init__.py/gcloud/__init__.py"
}