{
    "api_description": "is Google's NoSQL Big Data database service. It's the\nsame database that powers many core Google services, including Search,\nAnalytics, Maps, and Gmail.",
    "api_id": "bigtable.googleapis.com",
    "api_shortname": "bigtable",
    "client_documentation": "https://cloud.google.com/python/docs/reference/bigtable/latest",
    "default_version": "v2",
    "distribution_name": "google-cloud-bigtable",
    "issue_tracker": "https://issuetracker.google.com/savedsearches/559777",
    "language": "python",
    "library_type": "GAPIC_COMBO",
    "name": "bigtable",
    "name_pretty": "Google Cloud Bigtable",
    "product_documentation": "https://cloud.google.com/bigtable",
    "release_level": "stable",
    "repo": "googleapis/google-cloud-python"
}