{
  "api_id": "bigquerymigration.googleapis.com",
  "api_shortname": "bigquerymigration",
  "client_documentation": "https://cloud.google.com/python/docs/reference/bigquerymigration/latest",
  "default_version": "v2",
  "distribution_name": "google-cloud-bigquery-migration",
  "issue_tracker": "https://issuetracker.google.com/savedsearches/559654",
  "language": "python",
  "library_type": "GAPIC_AUTO",
  "name": "bigquerymigration",
  "name_pretty": "Google BigQuery Migration",
  "product_documentation": "https://cloud.google.com/bigquery/docs/reference/migration/",
  "release_level": "preview",
  "repo": "googleapis/google-cloud-python",
  "requires_billing": true
}